<?xml version="1.0"?>
<!--
/**
 * @author andy
 * @email andyworkbase@gmail.com
 * @team MageCloud
 * @package MageCloud_EnhancedEcommerce
 */
-->
<page xmlns:xsi="http://www.w3.org/2001/XMLSchema-instance" xsi:noNamespaceSchemaLocation="urn:magento:framework:View/Layout/etc/page_configuration.xsd">
    <body>
        <referenceBlock name="after.body.start">
            <block class="MageCloud\EnhancedEcommerce\Block\Catalog\Product\ViewItemList"
                   name="magecloud.enhanced.ecommerce.catalog.product.view-item-list">
                <arguments>
                    <argument name="viewModel" xsi:type="object">DataLayerViewModelViewItemList</argument>
                    <argument name="product_list_block_name" xsi:type="string">category.products.list</argument>
                </arguments>
            </block>
        </referenceBlock>
    </body>
</page>
